xdg_binary_cache/__init__.py
xdg_binary_cache/py.typed
xdg_binary_cache-1.5.dist-info/LICENSE
xdg_binary_cache-1.5.dist-info/METADATA
xdg_binary_cache-1.5.dist-info/WHEEL
xdg_binary_cache-1.5.dist-info/top_level.txt
xdg_binary_cache-1.5.dist-info/RECORD
