Metadata-Version: 2.1
Name: xdg-binary-cache
Version: 1.5
Summary: A library for downloading pre-compiled binaries to XDG_CACHE
Home-page: https://github.com/EliRibble/xdg-binary-cache
Author: Eli Ribble
Author-email: eliribble@google.com
License: UNKNOWN
Platform: UNKNOWN
Classifier: Intended Audience :: Developers
Classifier: License :: OSI Approved :: MIT License
Classifier: Programming Language :: Python
Classifier: Programming Language :: Python :: 3.6
Requires-Python: >=3.6
Provides-Extra: develop
Requires-Dist: mypy ; extra == 'develop'
Requires-Dist: nose2 ; extra == 'develop'
Requires-Dist: pylint ; extra == 'develop'
Requires-Dist: twine ; extra == 'develop'
Requires-Dist: wheel ; extra == 'develop'
